main.py
hellopackjuanprojectsigma-0.1.0.dist-info/METADATA
hellopackjuanprojectsigma-0.1.0.dist-info/WHEEL
hellopackjuanprojectsigma-0.1.0.dist-info/top_level.txt
hellopackjuanprojectsigma-0.1.0.dist-info/RECORD
