Metadata-Version: 2.2
Name: Hellopackjuanprojectsigma
Version: 0.1.0
Summary: This is a pack for Hello World
Requires-Python: >=3.12
